CHANGES.txt
IDEAS.txt
LICENCE.txt
MANIFEST.in
README.md
setup.py
bin/upload_rotate.py
dcu/__init__.py
dcu.active_memory.egg-info/PKG-INFO
dcu.active_memory.egg-info/SOURCES.txt
dcu.active_memory.egg-info/dependency_links.txt
dcu.active_memory.egg-info/requires.txt
dcu.active_memory.egg-info/top_level.txt
dcu/active_memory/__init__.py
dcu/active_memory/rotate.py
dcu/active_memory/upload.py