Metadata-Version: 1.0
Name: dcu.active-memory
Version: 0.3.0
Summary: Script to rotate backup files on AWS S3 according to a grandfather, father, son strategy.
Home-page: https://github.com/dirkcuys/active-memory
Author: Dirk Uys
Author-email: dirkcuys@gmail.com
License: MIT
Platform: UNKNOWN
